hungovercoders_repo_tools/__init__.py
hungovercoders_repo_tools/complexity.py
hungovercoders_repo_tools/greetings.py
hungovercoders_repo_tools/py.typed
hungovercoders_repo_tools/todo.py
hungovercoders_repo_tools-0.1.93.dist-info/METADATA
hungovercoders_repo_tools-0.1.93.dist-info/WHEEL
hungovercoders_repo_tools-0.1.93.dist-info/entry_points.txt
hungovercoders_repo_tools-0.1.93.dist-info/RECORD
