Metadata-Version: 2.4
Name: hungovercoders_repo_tools
Version: 0.1.93
Summary: hungovercoders repository tools for managing and monitoring quality of repositories.
Author-email: dataGriff <info@hungovercoders.com>
Requires-Python: >=3.12
